{
  "parent": "minecraft:recipes/root",
  "criteria": {
    "has_cobblestone_eighteen_item": {
      "conditions": {
        "items": [
          {
            "items": [
              "tcc:cobblestone_eighteen_item"
            ]
          }
        ]
      },
      "trigger": "minecraft:inventory_changed"
    },
    "has_the_recipe": {
      "conditions": {
        "recipe": "minecraft:decompressed_cobblestone_eighteen"
      },
      "trigger": "minecraft:recipe_unlocked"
    }
  },
  "requirements": [
    [
      "has_cobblestone_eighteen_item",
      "has_the_recipe"
    ]
  ],
  "rewards": {
    "recipes": [
      "minecraft:decompressed_cobblestone_eighteen"
    ]
  },
  "sends_telemetry_event": false
}